indicatortest/CHANGELOG.md
indicatortest/__init__.py
indicatortest/indicatorbase.py
indicatortest/indicatortest.py
indicatortest/icons/indicatortest-symbolic.svg
indicatortest/icons/indicatortest.svg
indicatortest/locale/indicatortest.pot
indicatortest/locale/ru/LC_MESSAGES/indicatortest.mo
indicatortest/locale/ru/LC_MESSAGES/indicatortest.po
indicatortest/platform/linux/indicatortest.py.desktop
indicatortest/platform/linux/indicatortest.sh
indicatortest-1.0.16.dist-info/METADATA
indicatortest-1.0.16.dist-info/WHEEL
indicatortest-1.0.16.dist-info/top_level.txt
indicatortest-1.0.16.dist-info/RECORD
